freshdeskclient/__init__.py
freshdeskclient/api.py
nn_freshdesk_client-0.0.4.dist-info/LICENSE
nn_freshdesk_client-0.0.4.dist-info/METADATA
nn_freshdesk_client-0.0.4.dist-info/WHEEL
nn_freshdesk_client-0.0.4.dist-info/top_level.txt
nn_freshdesk_client-0.0.4.dist-info/RECORD
