Metadata-Version: 2.1
Name: nn-freshdesk-client
Version: 0.0.4
Summary: Python SDK for Freshdesk API
Author: Nordic Nest
License: License text copyright (c) 2020 MariaDB Corporation Ab, All Rights Reserved.
Classifier: Programming Language :: Python :: 3
Classifier: Operating System :: OS Independent
Requires-Python: >=3.8
License-File: LICENSE
Requires-Dist: requests
